seqdetect/__init__.py
seqdetect/detect.py
seqdetect/gbwrite.py
seqdetect-0.1.dist-info/METADATA
seqdetect-0.1.dist-info/RECORD
seqdetect-0.1.dist-info/WHEEL
seqdetect-0.1.dist-info/entry_points.txt
seqdetect-0.1.dist-info/top_level.txt
